chonkie/__init__.py
chonkie/logger.py
chonkie/py.typed
chonkie/tokenizer.py
chonkie/chef/__init__.py
chonkie/chef/base.py
chonkie/chef/markdown.py
chonkie/chef/table.py
chonkie/chef/text.py
chonkie/chunker/__init__.py
chonkie/chunker/base.py
chonkie/chunker/code.py
chonkie/chunker/fast.py
chonkie/chunker/late.py
chonkie/chunker/neural.py
chonkie/chunker/recursive.py
chonkie/chunker/semantic.py
chonkie/chunker/sentence.py
chonkie/chunker/slumber.py
chonkie/chunker/table.py
chonkie/chunker/token.py
chonkie/chunker/c_extensions/merge.c
chonkie/chunker/c_extensions/merge.cpython-312-aarch64-linux-gnu.so
chonkie/chunker/c_extensions/savgol.c
chonkie/chunker/c_extensions/savgol.cpython-312-aarch64-linux-gnu.so
chonkie/chunker/c_extensions/split.c
chonkie/chunker/c_extensions/split.cpython-312-aarch64-linux-gnu.so
chonkie/cloud/__init__.py
chonkie/cloud/file.py
chonkie/cloud/pipeline.py
chonkie/cloud/chunker/__init__.py
chonkie/cloud/chunker/base.py
chonkie/cloud/chunker/code.py
chonkie/cloud/chunker/late.py
chonkie/cloud/chunker/neural.py
chonkie/cloud/chunker/recursive.py
chonkie/cloud/chunker/semantic.py
chonkie/cloud/chunker/sentence.py
chonkie/cloud/chunker/slumber.py
chonkie/cloud/chunker/token.py
chonkie/cloud/refineries/__init__.py
chonkie/cloud/refineries/base.py
chonkie/cloud/refineries/embeddings.py
chonkie/cloud/refineries/overlap.py
chonkie/embeddings/__init__.py
chonkie/embeddings/auto.py
chonkie/embeddings/azure_openai.py
chonkie/embeddings/base.py
chonkie/embeddings/catsu.py
chonkie/embeddings/cohere.py
chonkie/embeddings/gemini.py
chonkie/embeddings/jina.py
chonkie/embeddings/litellm.py
chonkie/embeddings/model2vec.py
chonkie/embeddings/openai.py
chonkie/embeddings/registry.py
chonkie/embeddings/sentence_transformer.py
chonkie/embeddings/voyageai.py
chonkie/experimental/__init__.py
chonkie/experimental/code.py
chonkie/experimental/code_registry.py
chonkie/fetcher/__init__.py
chonkie-1.5.2.dist-info/METADATA
chonkie-1.5.2.dist-info/WHEEL
chonkie-1.5.2.dist-info/top_level.txt
chonkie-1.5.2.dist-info/RECORD
chonkie-1.5.2.dist-info/licenses/LICENSE
