Metadata-Version: 2.4
Name: chonkie
Version: 1.5.2
Summary: 🦛 CHONK your texts with Chonkie ✨ - The no-nonsense chunking library
Author-email: Bhavnick Minhas <bhavnick@chonkie.ai>, Shreyash Nigam <shreyash@chonkie.ai>
Maintainer-email: Bhavnick Minhas <bhavnick@chonkie.ai>, Shreyash Nigam <shreyash@chonkie.ai>
License: MIT License
Project-URL: Homepage, https://github.com/chonkie-inc/chonkie
Project-URL: Documentation, https://docs.chonkie.ai
Project-URL: Bug Tracker, https://github.com/chonkie-inc/chonkie/issues
Keywords: chunking,rag,retrieval-augmented-generation,nlp,natural-language-processing,text-processing,text-analysis,text-chunking,artificial-intelligence,machine-learning
Classifier: Programming Language :: Python
Classifier: Programming Language :: Python :: 3
Classifier: Programming Language :: Python :: 3.10
Classifier: Programming Language :: Python :: 3.11
Classifier: Programming Language :: Python :: 3.12
Classifier: Programming Language :: Python :: 3.13
Classifier: Intended Audience :: Developers
Classifier: Intended Audience :: Science/Research
Classifier: Intended Audience :: Information Technology
Classifier: Topic :: Scientific/Engineering :: Artificial Intelligence
Classifier: Topic :: Scientific/Engineering :: Information Analysis
Classifier: Topic :: Text Processing :: Linguistic
Requires-Python: >=3.10
License-File: LICENSE
Requires-Dist: tqdm>=4.64.0
Requires-Dist: numpy>=2.0.0
Provides-Extra: hub
Requires-Dist: huggingface-hub>=0.24.0; extra == "hub"
Requires-Dist: jsonschema>=4.23.0; extra == "hub"
Provides-Extra: viz
Requires-Dist: rich>=13.0.0; extra == "viz"
Provides-Extra: table
Requires-Dist: pandas; extra == "table"
Requires-Dist: tabulate; extra == "table"
Requires-Dist: openpyxl; extra == "table"
Provides-Extra: tokenizers
Requires-Dist: tokenizers>=0.16.0; extra == "tokenizers"
Provides-Extra: tiktoken
Requires-Dist: tiktoken>=0.5.0; extra == "tiktoken"
Provides-Extra: code
Requires-Dist: tree-sitter>=0.20.0; extra == "code"
Requires-Dist: tree-sitter-language-pack>=0.7.0; extra == "code"
Requires-Dist: magika<1.1.0,>=0.6.0; extra == "code"
Provides-Extra: neural
Requires-Dist: transformers>=4.0.0; extra == "neural"
Requires-Dist: torch<3.0,>=2.0.0; extra == "neural"
Provides-Extra: fast
Requires-Dist: memchunk>=0.3.0; extra == "fast"
Provides-Extra: model2vec
Requires-Dist: tokenizers>=0.16.0; extra == "model2vec"
Requires-Dist: model2vec>=0.7.0; extra == "model2vec"
Requires-Dist: numpy<3.0,>=2.0.0; extra == "model2vec"
Provides-Extra: st
Requires-Dist: tokenizers>=0.16.0; extra == "st"
Requires-Dist: sentence-transformers>=3.0.0; extra == "st"
Requires-Dist: accelerate>=1.6.0; extra == "st"
Provides-Extra: openai
Requires-Dist: tiktoken>=0.5.0; extra == "openai"
Requires-Dist: openai>=1.0.0; extra == "openai"
Requires-Dist: pydantic>=2.0.0; extra == "openai"
Provides-Extra: semantic
Requires-Dist: tokenizers>=0.16.0; extra == "semantic"
Requires-Dist: model2vec>=0.3.0; extra == "semantic"
Provides-Extra: gemini
Requires-Dist: pydantic>=2.0.0; extra == "gemini"
Requires-Dist: google-genai>=1.0.0; extra == "gemini"
Provides-Extra: azure-openai
Requires-Dist: azure-identity>=1.23.0; extra == "azure-openai"
Requires-Dist: tiktoken>=0.5.0; extra == "azure-openai"
Requires-Dist: openai>=1.0.0; extra == "azure-openai"
Requires-Dist: pydantic>=2.0.0; extra == "azure-openai"
Provides-Extra: voyageai
Requires-Dist: tokenizers>=0.16.0; extra == "voyageai"
Requires-Dist: voyageai>=0.3.2; extra == "voyageai"
Provides-Extra: cohere
Requires-Dist: tokenizers>=0.16.0; extra == "cohere"
Requires-Dist: cohere>=5.13.0; extra == "cohere"
Provides-Extra: jina
Requires-Dist: tokenizers>=0.16.0; extra == "jina"
Provides-Extra: catsu
Requires-Dist: catsu>=0.0.1; extra == "catsu"
Provides-Extra: litellm
Requires-Dist: litellm>=1.0.0; extra == "litellm"
Requires-Dist: tiktoken>=0.5.0; extra == "litellm"
Requires-Dist: tokenizers>=0.16.0; extra == "litellm"
Provides-Extra: chroma
Requires-Dist: chromadb>=1.0.0; extra == "chroma"
Provides-Extra: qdrant
Requires-Dist: qdrant-client>=1.0.0; extra == "qdrant"
Provides-Extra: tpuf
Requires-Dist: turbopuffer~=1.0; extra == "tpuf"
Provides-Extra: pgvector
Requires-Dist: vecs>=0.4.0; extra == "pgvector"
Provides-Extra: weaviate
Requires-Dist: weaviate-client>=4.16.7; extra == "weaviate"
Provides-Extra: datasets
Requires-Dist: datasets>=4.0.0; extra == "datasets"
Provides-Extra: pinecone
Requires-Dist: pinecone; extra == "pinecone"
Provides-Extra: mongodb
Requires-Dist: pymongo; extra == "mongodb"
Provides-Extra: elastic
Requires-Dist: elasticsearch>=8.0.0; extra == "elastic"
Provides-Extra: milvus
Requires-Dist: pymilvus>=2.1.0; extra == "milvus"
Provides-Extra: genie
Requires-Dist: pydantic>=2.0.0; extra == "genie"
Requires-Dist: google-genai>=1.0.0; extra == "genie"
Provides-Extra: all
Requires-Dist: httpx; extra == "all"
Requires-Dist: tokenizers>=0.16.0; extra == "all"
Requires-Dist: tiktoken>=0.5.0; extra == "all"
Requires-Dist: rich>=13.0.0; extra == "all"
Requires-Dist: tree-sitter>=0.20.0; extra == "all"
Requires-Dist: tree-sitter-language-pack>=0.7.0; extra == "all"
Requires-Dist: magika<1.1.0,>=0.6.0; extra == "all"
Requires-Dist: sentence-transformers>=3.0.0; extra == "all"
Requires-Dist: openai>=1.0.0; extra == "all"
Requires-Dist: model2vec>=0.7.0; extra == "all"
Requires-Dist: cohere>=5.13.0; extra == "all"
Requires-Dist: voyageai>=0.3.2; extra == "all"
Requires-Dist: accelerate>=1.6.0; extra == "all"
Requires-Dist: huggingface-hub>=0.24.0; extra == "all"
Requires-Dist: jsonschema>=4.23.0; extra == "all"
Requires-Dist: pydantic>=2.0.0; extra == "all"
Requires-Dist: google-genai>=1.0.0; extra == "all"
Requires-Dist: transformers>=4.0.0; extra == "all"
Requires-Dist: torch<3.0,>=2.0.0; extra == "all"
Requires-Dist: chromadb>=1.0.0; extra == "all"
Requires-Dist: qdrant-client>=1.0.0; extra == "all"
Requires-Dist: turbopuffer~=1.0; extra == "all"
Requires-Dist: weaviate-client>=4.16.7; extra == "all"
Requires-Dist: azure-identity>=1.23.0; extra == "all"
Requires-Dist: pinecone; extra == "all"
Requires-Dist: pymongo; extra == "all"
Requires-Dist: voyageai>=0.3.2; extra == "all"
Requires-Dist: vecs>=0.4.0; extra == "all"
Requires-Dist: pandas; extra == "all"
Requires-Dist: tabulate; extra == "all"
Requires-Dist: openpyxl; extra == "all"
Requires-Dist: elasticsearch>=8.0.0; extra == "all"
Requires-Dist: pymilvus>=2.1.0; extra == "all"
Requires-Dist: catsu>=0.0.1; extra == "all"
Requires-Dist: litellm>=1.0.0; extra == "all"
Requires-Dist: datasets>=1.14.0; extra == "all"
Requires-Dist: memchunk>=0.3.0; extra == "all"
Provides-Extra: dev
Requires-Dist: datasets>=1.14.0; extra == "dev"
Requires-Dist: transformers>=4.0.0; extra == "dev"
Requires-Dist: pytest>=6.2.0; extra == "dev"
Requires-Dist: pytest-cov>=4.0.0; extra == "dev"
Requires-Dist: pytest-xdist>=2.5.0; extra == "dev"
Requires-Dist: pytest-asyncio>=0.26.0; extra == "dev"
Requires-Dist: coverage; extra == "dev"
Requires-Dist: ruff>=0.0.265; extra == "dev"
Requires-Dist: mypy>=1.11.0; extra == "dev"
Requires-Dist: cython>=3.0.0; extra == "dev"
Requires-Dist: pandas; extra == "dev"
Requires-Dist: tabulate; extra == "dev"
Requires-Dist: openpyxl; extra == "dev"
Requires-Dist: uv>=0.9.18; extra == "dev"
Dynamic: license-file
